[
    {
        "company": "WIX",
        "className": "wix",
        "image_src": "wixengineering.svg"
    },
    {
        "company": "Fundbox",
        "className": "fundbox",
        "image_src": "fundbox.svg"
    },
    {
        "company": "MyHeritage",
        "className": "myheritage",
        "image_src": "myheritage.svg"
    },
    {
        "company": "Autodesk",
        "className": "autodesk",
        "image_src": "autodesk.svg"
    },
    {
        "company": "Cloudinary",
        "className": "cloudinary",
        "image_src": "cloudinary.svg"
    },
    {
        "company": "AT&T",
        "className": "at_and_t",
        "image_src": "at_and_t.svg"
    },
    {
        "company": "DaPulse",
        "className": "dapulse",
        "image_src": "dapulse.png"
    },
    {
        "company": "Facebook",
        "className": "facebook",
        "image_src": "facebook.png"
    },
    {
        "company": "Tailor Brand",
        "className": "tailor_brand",
        "image_src": "tailor_brand.png"
    },
    {
        "company": "Neuland",
        "className": "neuland",
        "image_src": "neuland.svg"
    },
    {
        "company": "Taboola",
        "className": "taboola",
        "image_src": "taboola.png"
    }
]