{
    "all": [{
        "first_name": "Sergey",
        "last_name": "Bolshchikov",
        "position": "Tech Lead",
        "image_src": "sergey_bolshchikov",
        "image_format": "landscape"
    }, {
        "first_name": "Tom",
        "last_name": "Raviv",
        "position": "Application Developer",
        "image_src": "tom_raviv",
        "image_format": "portrait"
    }, {
        "first_name": "Igal",
        "last_name": "Steklov",
        "position": "Developer",
        "image_src": "igal_steklov",
        "image_format": "landscape"
    }, {
        "first_name": "Oren",
        "last_name": "Shtang",
        "position": "Application Developer",
        "image_src": "oren_shtang",
        "image_format": "portrait"
    }, {
        "first_name": "Anna",
        "last_name": "Fridman & Simba",
        "position": "Application Developer",
        "image_src": "anna_fridman",
        "image_format": "landscape"
    }, {
        "first_name": "Yogev",
        "last_name": "Ahuvia",
        "position": "Application Developer",
        "image_src": "yogev_ahuvia",
        "image_format": "portrait"
    }, {
        "first_name": "Adir",
        "last_name": "Amsalem",
        "position": "Application Developer",
        "image_src": "adir_amsalem",
        "image_format": "portrait"
    }, {
        "first_name": "Danielle",
        "last_name": "Kanish",
        "position": "Application Developer",
        "image_src": "danielle_kanish",
        "image_format": "portrait"
    }, {
        "first_name": "Ella",
        "last_name": "Moscovitz",
        "position": "Application Developer",
        "image_src": "ella_moscovitz",
        "image_format": "landscape"
    }, {
        "first_name": "Mor",
        "last_name": "Gilad",
        "position": "Application Developer",
        "image_src": "mor_gilad",
        "image_format": "portrait"
    }, {
        "first_name": "Yaron",
        "last_name": "Shavit",
        "position": "Application Developer",
        "image_src": "yaron_shavit",
        "image_format": "landscape"
    }]
}


